setup.py
abdu/__init__.py
abdu.egg-info/PKG-INFO
abdu.egg-info/SOURCES.txt
abdu.egg-info/dependency_links.txt
abdu.egg-info/not-zip-safe
abdu.egg-info/top_level.txt
abdu/Prediction/ClassModel.py
abdu/Prediction/__init__.py
abdu/dataCollect/DataCollection.py
abdu/ot/Load_db.py
abdu/ot/__init__.py